dexie_rewards/__init__.py
dexie_rewards/abc.py
dexie_rewards/config.py
dexie_rewards/decorators/with_db_connection.py
dexie_rewards/main.py
dexie_rewards/rewards/claim.py
dexie_rewards/rewards/list.py
dexie_rewards/rewards/main.py
dexie_rewards/rewards/utils.py
dexie_rewards/services/database.py
dexie_rewards/services/dexie_api.py
dexie_rewards/services/wallet_rpc_client.py
dexie_rewards/types/offer_reward.py
dexie_rewards/types/offers.py
dexie_rewards/types/utils.py
dexie_rewards/utils.py
dexie_rewards-2.5.0.dist-info/LICENSE
dexie_rewards-2.5.0.dist-info/METADATA
dexie_rewards-2.5.0.dist-info/WHEEL
dexie_rewards-2.5.0.dist-info/entry_points.txt
dexie_rewards-2.5.0.dist-info/RECORD
