Metadata-Version: 2.1
Name: dexie-rewards
Version: 2.5.0
Summary: dexie-rewards is a Python CLI helper tool designed automatically to claim dexie liquidity rewards for offers created using the official Chia Wallet.
License: Apache-2.0
Author: Dexie Contributors
Author-email: pypi@dexie.space
Requires-Python: >=3.9,<3.13
Classifier: License :: OSI Approved :: Apache Software License
Classifier: Programming Language :: Python :: 3
Classifier: Programming Language :: Python :: 3.9
Classifier: Programming Language :: Python :: 3.10
Classifier: Programming Language :: Python :: 3.11
Classifier: Programming Language :: Python :: 3.12
Requires-Dist: aiohttp (==3.10.4)
Requires-Dist: aiomisc[aiohttp,rich] (>=17.5.31,<18.0.0)
Requires-Dist: aiosqlite (>=0.17.0)
Requires-Dist: based58 (>=0.1.1,<0.2.0)
Requires-Dist: rich-click (>=1.8.5,<2.0.0)
